cch_mcp_demo/__init__.py
cch_mcp_demo-0.1.0.dist-info/WHEEL
cch_mcp_demo-0.1.0.dist-info/entry_points.txt
cch_mcp_demo-0.1.0.dist-info/METADATA
cch_mcp_demo-0.1.0.dist-info/RECORD
