Metadata-Version: 2.3
Name: cch-mcp-demo
Version: 0.1.0
Summary: Add your description here
Author: CCH
Author-email: CCH <489285050@qq.com>
Requires-Dist: mcp[cli]>=1.12.3
Requires-Python: >=3.11.3
